pcmd/__const__.py
pcmd/__core__.py
pcmd/__echoes__.py
pcmd/__helper__.py
pcmd/__init__.py
pcmd/__main__.py
pcmd/main.py
pcmd/tryouts/tryout_add.py
pcmd/tryouts/tryout_run_args.py
pcmd/tryouts/tryout_template.py
pcmd-2.3.0.dist-info/entry_points.txt
pcmd-2.3.0.dist-info/LICENSE
pcmd-2.3.0.dist-info/WHEEL
pcmd-2.3.0.dist-info/METADATA
pcmd-2.3.0.dist-info/RECORD
