Metadata-Version: 2.1
Name: pcmd
Version: 2.3.0
Summary: A super simple terminal command shortener.
Home-page: https://github.com/j0fiN/pcmd
License: Apache-2.0
Keywords: command-line,utilities,cmd,terminal,CLI
Author: Jofin
Author-email: jofinfab@gmail.com
Requires-Python: >=3.6,<4.0
Classifier: License :: OSI Approved :: Apache Software License
Classifier: Programming Language :: Python :: 3
Classifier: Programming Language :: Python :: 3.10
Classifier: Programming Language :: Python :: 3.6
Classifier: Programming Language :: Python :: 3.7
Classifier: Programming Language :: Python :: 3.8
Classifier: Programming Language :: Python :: 3.9
Classifier: Topic :: Software Development :: Build Tools
Classifier: Topic :: Utilities
Requires-Dist: Distance
Requires-Dist: PyYAML
Requires-Dist: typer
Project-URL: Repository, https://github.com/j0fiN/pcmd
